setup.py
gbh_tasks.egg-info/PKG-INFO
gbh_tasks.egg-info/SOURCES.txt
gbh_tasks.egg-info/dependency_links.txt
gbh_tasks.egg-info/top_level.txt
tasks/__init__.py
tasks/single.py
tasks/test/__init__.py
tasks/test/single_test.py