Metadata-Version: 1.0
Name: gbh-tasks
Version: 0.2
Summary: 90 days tasks
Home-page: UNKNOWN
Author: Gal Ben Haim
Author-email: galbh2@gmail.com
License: UNKNOWN
Platform: UNKNOWN
